database.py
main.py
schemas.py
tests/integration/__init_..py
tests/integration/test_file_expiry.py
web_file_uploader-0.2.0.dist-info/METADATA
web_file_uploader-0.2.0.dist-info/WHEEL
web_file_uploader-0.2.0.dist-info/entry_points.txt
web_file_uploader-0.2.0.dist-info/top_level.txt
web_file_uploader-0.2.0.dist-info/RECORD
